{
  "project_info": {
    "project_id": "choose-helper",
    "project_number": "478438458430",
    "name": "Choose Helper"
  },
  "client": [
    {
      "client_info": {
        "mobilesdk_app_id": "1:478438458430:android:f50d296c5106c780",
        "client_id": "android:com.geekhub.choosehelper",
        "client_type": 1,
        "android_client_info": {
          "package_name": "com.geekhub.choosehelper"
        }
      },
      "oauth_client": [
        {
          "client_id": "478438458430-m6gua7au0d1c1uh2gb1s9l2fqkflm4v0.apps.googleusercontent.com",
          "client_type": 1,
          "android_info": {
            "package_name": "com.geekhub.choosehelper",
            "certificate_hash": "FDE19227E29790CE8ECB53E05D42FFB9A8BA6457"
          }
        },
        {
          "client_id": "478438458430-6v9h777dnn8qcaqk70dkg0k6lgnckl9i.apps.googleusercontent.com",
          "client_type": 3
        }
      ],
      "api_key": [],
      "services": {
        "analytics_service": {
          "status": 1
        },
        "cloud_messaging_service": {
          "status": 1,
          "apns_config": []
        },
        "appinvite_service": {
          "status": 1,
          "other_platform_oauth_client": []
        },
        "google_signin_service": {
          "status": 2
        },
        "ads_service": {
          "status": 1
        }
      }
    }
  ],
  "client_info": [],
  "ARTIFACT_VERSION": "1"
}